odoo/addons/product_supplierinfo_barcode/README.rst
odoo/addons/product_supplierinfo_barcode/__init__.py
odoo/addons/product_supplierinfo_barcode/__manifest__.py
odoo/addons/product_supplierinfo_barcode/i18n/de.po
odoo/addons/product_supplierinfo_barcode/i18n/product_supplierinfo_barcode.pot
odoo/addons/product_supplierinfo_barcode/models/__init__.py
odoo/addons/product_supplierinfo_barcode/models/supplierinfo.py
odoo/addons/product_supplierinfo_barcode/readme/CONTRIBUTORS.rst
odoo/addons/product_supplierinfo_barcode/readme/DESCRIPTION.rst
odoo/addons/product_supplierinfo_barcode/static/description/icon.png
odoo/addons/product_supplierinfo_barcode/static/description/index.html
odoo/addons/product_supplierinfo_barcode/views/product_views.xml
odoo/addons/product_supplierinfo_barcode/views/supplierinfo_views.xml
odoo14_addon_product_supplierinfo_barcode-14.0.1.1.0.dist-info/METADATA
odoo14_addon_product_supplierinfo_barcode-14.0.1.1.0.dist-info/WHEEL
odoo14_addon_product_supplierinfo_barcode-14.0.1.1.0.dist-info/top_level.txt
odoo14_addon_product_supplierinfo_barcode-14.0.1.1.0.dist-info/RECORD
