Metadata-Version: 2.1
Name: odoo14-addon-product-supplierinfo-barcode
Version: 14.0.1.1.0
Summary: Add a barcode to supplier pricelist items
Home-page: https://github.com/OCA/stock-logistics-barcode
Author: TAKOBI, Odoo Community Association (OCA)
Author-email: support@odoo-community.org
License: LGPL-3
Platform: UNKNOWN
Classifier: Programming Language :: Python
Classifier: Framework :: Odoo
Classifier: Framework :: Odoo :: 14.0
Classifier: License :: OSI Approved :: GNU Lesser General Public License v3 (LGPLv3)
Classifier: Development Status :: 4 - Beta
Requires-Python: >=3.6
Requires-Dist: odoo (<14.1dev,>=14.0a)
